{
  "language": "nl",
  "source_url": "https://eur-lex.europa.eu/legal-content/NL/TXT/HTML/?uri=CELEX:52023AP0236",
  "source_celex": "52023AP0236",
  "scraped_at": "2026-04-24T15:37:53Z",
  "version": "parliament-2023",
  "amendment_number": "362",
  "amendment_target": "Voorstel voor een verordening — Artikel 23 — titel",
  "body_md": "**Doel:** Voorstel voor een verordening — Artikel 23 — titel\n\n## Door de Commissie voorgestelde tekst\n\nSamenwerking met bevoegde autoriteiten\n\n## Amendement van het Europees Parlement\n\nSamenwerking met bevoegde autoriteiten , het AI-bureau en de Commissie\n",
  "commission_text": "Samenwerking met bevoegde autoriteiten",
  "parliament_text": "Samenwerking met bevoegde autoriteiten , het AI-bureau en de Commissie",
  "char_count": 108
}